{
  "videos": [
    {
      "caption": "Thaniye",
      "imageLink": "https://i.scdn.co/image/ab67616d0000b27355f6f8be641399a5f283ff23",
      "videoLink": "https://www.youtube.com/embed/l0yU-mcCM9I",
      "id": 13
    },
    {
      "caption": "Nee illamal Naan illaye",
      "imageLink": "https://c.saavncdn.com/032/Vishwaroopam-Tamil--Tamil-2012-20190822132700-500x500.jpg",
      "videoLink": "https://www.youtube.com/embed/p7GmO8ewjmw",
      "id": 14
    },
    {
      "caption": "Thaarame",
      "imageLink": "https://m.media-amazon.com/images/M/MV5BZGUzZmY2NDgtZmIwMC00ZDY1LTk4NmItYWU4MDlkZjk3ZWVhXkEyXkFqcGc@._V1_.jpg",
      "videoLink": "https://www.youtube.com/embed/gB1gPmtDohY",
      "id": 15
    },
    {
      "caption": "Kalaabhakkara",
      "imageLink": "https://m.media-amazon.com/images/M/MV5BYjEwMTMzM2QtYjdjYy00ZjEwLTk0NDQtNDBmNWIzM2Y3ZGQ2XkEyXkFqcGc@._V1_.jpg",
      "videoLink": "https://www.youtube.com/embed/VzT2xurZrbI",
      "id": 16
    }
  ],
  "categories": [
    {
      "categoryName": "English",
      "allVideo": [],
      "id": 3
    },
    {
      "categoryName": "Tamil ",
      "allVideo": [],
      "id": 4
    },
    {
      "categoryName": "Hindi ",
      "allVideo": [],
      "id": 6
    }
  ],
  "history": [
    {
      "caption": "7 Rings",
      "videoLink": "https://www.youtube.com/embed/U6imB8nrw&s",
      "time": "14-3-2025   12:05:14",
      "id": 1
    },
    {
      "caption": "Kalaabhakkara",
      "videoLink": "https://www.youtube.com/embed/VzT2xurZrbI",
      "time": "17-3-2025   11:03:11",
      "id": 2
    },
    {
      "caption": "Nee illamal Naan illaye",
      "videoLink": "https://www.youtube.com/embed/p7GmO8ewjmw",
      "time": "17-3-2025   11:41:36",
      "id": 3
    },
    {
      "caption": "Kalaabhakkara",
      "videoLink": "https://www.youtube.com/embed/VzT2xurZrbI",
      "time": "17-3-2025   11:57:23",
      "id": 5
    }
  ]
}